{
  "$schema": "https://mintlify.com/docs.json",
  "theme": "maple",
  "name": "Palantrix - AI Video Interviews",
  "colors": {
    "primary": "#542694",
    "light": "#9b08bd",
    "dark": "#2f1480"
  },
  "favicon": "/favicon.ico",
  "navigation": {
    "tabs": [
      {
        "tab": "Introduction",
        "groups": [
          {
            "group": "Welcome",
            "pages": [
              "index"
            ]
          },
          {
            "group": "How To - Candidates",
            "icon": "user-check",
            "pages": [
              "Create your Account",
              "Set up your Profile",
              "Mock Interviews",
              "Create Interview Plans",
              "Apply for a Job",
              "Certification"
            ]
          },
          {
            "group": "How To - Companies",
            "icon": "user-check",
            "pages": [
              "Create your Account",
              "Set up your Profile",
              "Post a Job",
              "Palantrix Recruitment Pipeline",
              "Follow-Up Video Interviews",
              "Candidate Comms",
              "Team Management"
            ]
          }
        ]
      },
      {
        "tab": "Candidates",
        "groups": [
          {
            "group": "Overview",
            "pages": [
              "candidates/introduction"
            ]
          }
        ]
      },
      {
        "tab": "Companies",
        "groups": [
          {
            "group": "Overview",
            "pages": [
              "companies/introduction"
            ]
          }
        ]
      },
      {
        "tab": "Educators",
        "groups": [
          {
            "group": "Overview",
            "pages": [
              "educators/introduction"
            ]
          }
        ]
      },
      {
        "tab": "Plans",
        "groups": [
          {
            "group": "Overview",
            "pages": [
              "plans/introduction"
            ]
          }
        ]
      },
      {
        "tab": "Compliance",
        "groups": [
          {
            "group": "Overview",
            "pages": [
              "compliance/introduction"
            ]
          }
        ]
      },
      {
        "tab": "FAQ",
        "groups": [
          {
            "group": "Overview",
            "pages": [
              "faq/introduction"
            ]
          }
        ]
      }
    ],
    "global": {
      "anchors": [
      ]
    }
  },
  "logo": {
    "light": "/logo/light.png",
    "dark": "/logo/dark.png"
  },
  "navbar": {
    "links": [
      {
        "label": "Support",
        "href": "mailto:support@palantrix.com"
      }
    ]
  }
}